proxpi/__init__.py
proxpi/_cache.py
proxpi/server.py
proxpi/templates/files.html
proxpi/templates/index.html
proxpi/templates/packages.html
proxpi-1.2.2.dist-info/licenses/LICENSE
proxpi-1.2.2.dist-info/METADATA
proxpi-1.2.2.dist-info/WHEEL
proxpi-1.2.2.dist-info/top_level.txt
proxpi-1.2.2.dist-info/RECORD
