Metadata-Version: 2.4
Name: proxpi
Version: 1.2.2
Summary: PyPI caching mirror
Home-page: https://github.com/EpicWink/proxpi
Author: Laurie O
Author-email: laurie_opperman@hotmail.com
License: MIT
Keywords: pypi,index,mirror,cache
Classifier: Environment :: Console
Classifier: Intended Audience :: Developers
Classifier: Programming Language :: Python :: 3 :: Only
Classifier: Natural Language :: English
Classifier: Operating System :: POSIX :: Linux
Classifier: Operating System :: Microsoft :: Windows
Requires-Python: ~=3.6
License-File: LICENSE
Requires-Dist: dataclasses>=0.6; python_version < "3.7"
Requires-Dist: flask<4.0,>=2.0
Requires-Dist: jinja2~=3.0
Requires-Dist: lxml<6.0,>=4.8
Requires-Dist: requests~=2.27
Dynamic: license-file
